<?xml version = '1.0' encoding = 'UTF-8'?>
<FKIndexAssociation class="oracle.dbtools.crest.model.design.relational.FKIndexAssociation" directorySegmentName="seg_0" id="E943C04E-06AC-7DF1-83CA-8F7C0A5BA764" containerWithKeyObject="B7D84EC8-91D8-1604-0DAF-46829C724F8E" localFKIndex="57D36AFD-44F9-6792-1641-419239C8EB0B" name="TBL_EMPLEADOS_TBL_LUGARES_FK">
<createdBy>erick.marin</createdBy>
<createdTime>2024-02-02 00:16:01 UTC</createdTime>
<ownerDesignName>db_unah</ownerDesignName>
<referredTableLongName>TBL_LUGARES</referredTableLongName>
<deleteRule>NO ACTION</deleteRule>
<referredTableID>FF243D8E-312B-7153-28CD-BC09A3830FDE</referredTableID>
<keyObject>AFFCFCEF-E6D7-DE97-28A0-43B91DCE0C3B</keyObject>
<referredKeyID>AFFCFCEF-E6D7-DE97-28A0-43B91DCE0C3B</referredKeyID>
<mandatory>true</mandatory>
<refColNames>CODIGO_LUGAR</refColNames>
<transferable>true</transferable>
<rely>false</rely>
<columnDependencyConstraintGenerateInDDL>true</columnDependencyConstraintGenerateInDDL>
</FKIndexAssociation>